asyncer-0.0.6.dist-info/METADATA
asyncer-0.0.6.dist-info/WHEEL
asyncer-0.0.6.dist-info/licenses/LICENSE
asyncer/__init__.py
asyncer/_main.py
asyncer/py.typed
asyncer-0.0.6.dist-info/RECORD
