Metadata-Version: 2.1
Name: asyncer
Version: 0.0.6
Summary: Asyncer, async and await, focused on developer experience.
Author-Email: =?utf-8?q?Sebasti=C3=A1n_Ram=C3=ADrez?= <tiangolo@gmail.com>
Classifier: Development Status :: 4 - Beta
Classifier: Framework :: AsyncIO
Classifier: Framework :: Trio
Classifier: Intended Audience :: Developers
Classifier: Intended Audience :: Education
Classifier: Intended Audience :: Information Technology
Classifier: Intended Audience :: Science/Research
Classifier: Intended Audience :: System Administrators
Classifier: License :: OSI Approved :: MIT License
Classifier: Programming Language :: Python :: 3 :: Only
Classifier: Programming Language :: Python :: 3.8
Classifier: Programming Language :: Python :: 3.9
Classifier: Programming Language :: Python :: 3.10
Classifier: Programming Language :: Python :: 3.11
Classifier: Programming Language :: Python :: 3.12
Classifier: Topic :: Internet
Classifier: Typing :: Typed
Project-URL: Homepage, https://github.com/tiangolo/asyncer
Project-URL: Documentation, https://asyncer.tiangolo.com
Project-URL: Repository, https://github.com/tiangolo/asyncer
Requires-Python: >=3.8
Requires-Dist: anyio<5.0,>=3.4.0
Requires-Dist: typing_extensions>=4.8.0; python_version < "3.10"
